calendarplus.py
calendar_plus-0.0.1.dist-info/LICENSE
calendar_plus-0.0.1.dist-info/METADATA
calendar_plus-0.0.1.dist-info/WHEEL
calendar_plus-0.0.1.dist-info/top_level.txt
calendar_plus-0.0.1.dist-info/RECORD
