Metadata-Version: 2.1
Name: calendar-plus
Version: 0.0.1
Summary: A calendar library for creating HTML calendars that contain query objects
Home-page: https://github.com/iyanuashiri/calendar-plus
Author: Iyanu Ajao
Author-email: ajaoiyanu@gmail.com
License: MIT
Platform: UNKNOWN
Classifier: License :: OSI Approved :: MIT License
Classifier: Programming Language :: Python
Classifier: Programming Language :: Python :: 3
Classifier: Programming Language :: Python :: 3.6
Classifier: Programming Language :: Python :: Implementation :: CPython
Classifier: Programming Language :: Python :: Implementation :: PyPy
Requires-Python: >=3.6.0
